nt2dc/__init__.py
nt2dc/builtins.py
nt2dc/dataclass.py
nt2dc/named_tuple.py
nt2dc-0.9.0.dist-info/METADATA
nt2dc-0.9.0.dist-info/WHEEL
nt2dc-0.9.0.dist-info/top_level.txt
nt2dc-0.9.0.dist-info/RECORD
