Metadata-Version: 2.1
Name: nt2dc
Version: 0.9.0
Summary: Converter for dataclasses and named tuples
Home-page: https://github.com/carstencodes/nt2dc
Author: Carsten Igel
Author-email: cig@bite-that-bit.de
License: BSD 3-Clause
Keywords: NamedTuple DataClasses
Platform: UNKNOWN
Classifier: Development Status :: 4 - Beta
Classifier: Intended Audience :: Developers
Classifier: License :: OSI Approved :: BSD License
Classifier: Operating System :: OS Independent
Classifier: Programming Language :: Python :: 3.8
Classifier: Programming Language :: Python :: 3.9
Classifier: Topic :: Software Development :: Libraries :: Python Modules
Classifier: Topic :: System
Classifier: Typing :: Typed
Requires-Python: >=3.8, < 4
